{
  "points": [
    {
      "lat": 28.5244,
      "lng": 77.1855,
      "timestamp": "2024-12-19T00:30:00.000Z",
      "speed": 0,
      "isStop": false
    },
    {
      "lat": 28.524736363636364,
      "lng": 77.19172727272728,
      "timestamp": "2024-12-19T00:35:00.000Z",
      "speed": 57,
      "isStop": false
    },
    {
      "lat": 28.52507272727273,
      "lng": 77.19795454545455,
      "timestamp": "2024-12-19T00:37:00.000Z",
      "speed": 49,
      "isStop": false
    },
    {
      "lat": 28.52540909090909,
      "lng": 77.20418181818182,
      "timestamp": "2024-12-19T00:39:00.000Z",
      "speed": 24,
      "isStop": false
    },
    {
      "lat": 28.525745454545454,
      "lng": 77.2104090909091,
      "timestamp": "2024-12-19T00:41:00.000Z",
      "speed": 43,
      "isStop": false
    },
    {
      "lat": 28.52608181818182,
      "lng": 77.21663636363637,
      "timestamp": "2024-12-19T00:43:00.000Z",
      "speed": 35,
      "isStop": false
    },
    {
      "lat": 28.526418181818183,
      "lng": 77.22286363636364,
      "timestamp": "2024-12-19T00:45:00.000Z",
      "speed": 34,
      "isStop": false
    },
    {
      "lat": 28.526754545454544,
      "lng": 77.22909090909091,
      "timestamp": "2024-12-19T00:47:00.000Z",
      "speed": 29,
      "isStop": false
    },
    {
      "lat": 28.52709090909091,
      "lng": 77.23531818181819,
      "timestamp": "2024-12-19T00:49:00.000Z",
      "speed": 83,
      "isStop": false
    },
    {
      "lat": 28.527427272727273,
      "lng": 77.24154545454546,
      "timestamp": "2024-12-19T00:51:00.000Z",
      "speed": 41,
      "isStop": false
    },
    {
      "lat": 28.527763636363638,
      "lng": 77.24777272727273,
      "timestamp": "2024-12-19T00:53:00.000Z",
      "speed": 62,
      "isStop": false
    },
    {
      "lat": 28.5281,
      "lng": 77.254,
      "timestamp": "2024-12-19T00:55:00.000Z",
      "speed": 37,
      "isStop": false
    },
    {
      "lat": 28.528436363636363,
      "lng": 77.26022727272728,
      "timestamp": "2024-12-19T00:57:00.000Z",
      "speed": 47,
      "isStop": false
    },
    {
      "lat": 28.528772727272727,
      "lng": 77.26645454545455,
      "timestamp": "2024-12-19T00:59:00.000Z",
      "speed": 29,
      "isStop": false
    },
    {
      "lat": 28.529109090909092,
      "lng": 77.27268181818182,
      "timestamp": "2024-12-19T01:01:00.000Z",
      "speed": 21,
      "isStop": false
    },
    {
      "lat": 28.529445454545453,
      "lng": 77.2789090909091,
      "timestamp": "2024-12-19T01:03:00.000Z",
      "speed": 48,
      "isStop": false
    },
    {
      "lat": 28.529781818181817,
      "lng": 77.28513636363637,
      "timestamp": "2024-12-19T01:05:00.000Z",
      "speed": 46,
      "isStop": false
    },
    {
      "lat": 28.53011818181818,
      "lng": 77.29136363636364,
      "timestamp": "2024-12-19T01:07:00.000Z",
      "speed": 49,
      "isStop": false
    },
    {
      "lat": 28.530454545454546,
      "lng": 77.29759090909091,
      "timestamp": "2024-12-19T01:09:00.000Z",
      "speed": 24,
      "isStop": false
    },
    {
      "lat": 28.530790909090907,
      "lng": 77.30381818181819,
      "timestamp": "2024-12-19T01:11:00.000Z",
      "speed": 61,
      "isStop": false
    },
    {
      "lat": 28.53112727272727,
      "lng": 77.31004545454546,
      "timestamp": "2024-12-19T01:13:00.000Z",
      "speed": 28,
      "isStop": false
    },
    {
      "lat": 28.531463636363636,
      "lng": 77.31627272727273,
      "timestamp": "2024-12-19T01:15:00.000Z",
      "speed": 50,
      "isStop": false
    },
    {
      "lat": 28.5318,
      "lng": 77.3225,
      "timestamp": "2024-12-19T01:17:00.000Z",
      "speed": 45,
      "isStop": false
    },
    {
      "lat": 28.53213636363636,
      "lng": 77.32872727272728,
      "timestamp": "2024-12-19T01:19:00.000Z",
      "speed": 46,
      "isStop": false
    },
    {
      "lat": 28.532472727272726,
      "lng": 77.33495454545455,
      "timestamp": "2024-12-19T01:21:00.000Z",
      "speed": 53,
      "isStop": false
    },
    {
      "lat": 28.53280909090909,
      "lng": 77.34118181818182,
      "timestamp": "2024-12-19T01:23:00.000Z",
      "speed": 42,
      "isStop": false
    },
    {
      "lat": 28.533145454545455,
      "lng": 77.3474090909091,
      "timestamp": "2024-12-19T01:25:00.000Z",
      "speed": 29,
      "isStop": false
    },
    {
      "lat": 28.533481818181816,
      "lng": 77.35363636363637,
      "timestamp": "2024-12-19T01:27:00.000Z",
      "speed": 33,
      "isStop": false
    },
    {
      "lat": 28.53381818181818,
      "lng": 77.35986363636364,
      "timestamp": "2024-12-19T01:29:00.000Z",
      "speed": 59,
      "isStop": false
    },
    {
      "lat": 28.534154545454545,
      "lng": 77.36609090909091,
      "timestamp": "2024-12-19T01:31:00.000Z",
      "speed": 50,
      "isStop": false
    },
    {
      "lat": 28.53449090909091,
      "lng": 77.37231818181819,
      "timestamp": "2024-12-19T01:33:00.000Z",
      "speed": 40,
      "isStop": false
    },
    {
      "lat": 28.53482727272727,
      "lng": 77.37854545454546,
      "timestamp": "2024-12-19T01:35:00.000Z",
      "speed": 39,
      "isStop": false
    },
    {
      "lat": 28.535163636363635,
      "lng": 77.38477272727273,
      "timestamp": "2024-12-19T01:37:00.000Z",
      "speed": 41,
      "isStop": false
    },
    {
      "lat": 28.5355,
      "lng": 77.391,
      "timestamp": "2024-12-19T01:39:00.000Z",
      "speed": 0,
      "isStop": false
    },
    {
      "lat": 28.5355,
      "lng": 77.391,
      "timestamp": "2024-12-19T02:13:00.000Z",
      "speed": 0,
      "isStop": false
    },
    {
      "lat": 28.54157727272727,
      "lng": 77.39385454545454,
      "timestamp": "2024-12-19T02:18:00.000Z",
      "speed": 47,
      "isStop": false
    },
    {
      "lat": 28.547654545454545,
      "lng": 77.3967090909091,
      "timestamp": "2024-12-19T02:20:00.000Z",
      "speed": 47,
      "isStop": false
    },
    {
      "lat": 28.553731818181816,
      "lng": 77.39956363636364,
      "timestamp": "2024-12-19T02:22:00.000Z",
      "speed": 47,
      "isStop": false
    },
    {
      "lat": 28.55980909090909,
      "lng": 77.40241818181819,
      "timestamp": "2024-12-19T02:24:00.000Z",
      "speed": 26,
      "isStop": false
    },
    {
      "lat": 28.565886363636363,
      "lng": 77.40527272727273,
      "timestamp": "2024-12-19T02:26:00.000Z",
      "speed": 24,
      "isStop": false
    },
    {
      "lat": 28.571963636363634,
      "lng": 77.40812727272727,
      "timestamp": "2024-12-19T02:28:00.000Z",
      "speed": 44,
      "isStop": false
    },
    {
      "lat": 28.57804090909091,
      "lng": 77.41098181818182,
      "timestamp": "2024-12-19T02:30:00.000Z",
      "speed": 47,
      "isStop": false
    },
    {
      "lat": 28.58411818181818,
      "lng": 77.41383636363636,
      "timestamp": "2024-12-19T02:32:00.000Z",
      "speed": 52,
      "isStop": false
    },
    {
      "lat": 28.590195454545455,
      "lng": 77.41669090909092,
      "timestamp": "2024-12-19T02:34:00.000Z",
      "speed": 84,
      "isStop": false
    },
    {
      "lat": 28.596272727272726,
      "lng": 77.41954545454546,
      "timestamp": "2024-12-19T02:36:00.000Z",
      "speed": 40,
      "isStop": false
    },
    {
      "lat": 28.60235,
      "lng": 77.42240000000001,
      "timestamp": "2024-12-19T02:38:00.000Z",
      "speed": 45,
      "isStop": false
    },
    {
      "lat": 28.608427272727273,
      "lng": 77.42525454545455,
      "timestamp": "2024-12-19T02:40:00.000Z",
      "speed": 43,
      "isStop": false
    },
    {
      "lat": 28.614504545454544,
      "lng": 77.42810909090909,
      "timestamp": "2024-12-19T02:42:00.000Z",
      "speed": 105,
      "isStop": false
    },
    {
      "lat": 28.62058181818182,
      "lng": 77.43096363636364,
      "timestamp": "2024-12-19T02:44:00.000Z",
      "speed": 49,
      "isStop": false
    },
    {
      "lat": 28.62665909090909,
      "lng": 77.43381818181818,
      "timestamp": "2024-12-19T02:46:00.000Z",
      "speed": 30,
      "isStop": false
    },
    {
      "lat": 28.632736363636365,
      "lng": 77.43667272727274,
      "timestamp": "2024-12-19T02:48:00.000Z",
      "speed": 84,
      "isStop": false
    },
    {
      "lat": 28.638813636363636,
      "lng": 77.43952727272728,
      "timestamp": "2024-12-19T02:50:00.000Z",
      "speed": 87,
      "isStop": false
    },
    {
      "lat": 28.644890909090908,
      "lng": 77.44238181818181,
      "timestamp": "2024-12-19T02:52:00.000Z",
      "speed": 52,
      "isStop": false
    },
    {
      "lat": 28.650968181818183,
      "lng": 77.44523636363637,
      "timestamp": "2024-12-19T02:54:00.000Z",
      "speed": 58,
      "isStop": false
    },
    {
      "lat": 28.657045454545454,
      "lng": 77.44809090909091,
      "timestamp": "2024-12-19T02:56:00.000Z",
      "speed": 50,
      "isStop": false
    },
    {
      "lat": 28.66312272727273,
      "lng": 77.45094545454546,
      "timestamp": "2024-12-19T02:58:00.000Z",
      "speed": 36,
      "isStop": false
    },
    {
      "lat": 28.6692,
      "lng": 77.4538,
      "timestamp": "2024-12-19T03:00:00.000Z",
      "speed": 0,
      "isStop": false
    },
    {
      "lat": 28.6692,
      "lng": 77.4538,
      "timestamp": "2024-12-19T03:16:00.000Z",
      "speed": 0,
      "isStop": false
    },
    {
      "lat": 28.670945,
      "lng": 77.436235,
      "timestamp": "2024-12-19T03:21:00.000Z",
      "speed": 55,
      "isStop": false
    },
    {
      "lat": 28.67269,
      "lng": 77.41867,
      "timestamp": "2024-12-19T03:23:00.000Z",
      "speed": 37,
      "isStop": false
    },
    {
      "lat": 28.674435,
      "lng": 77.401105,
      "timestamp": "2024-12-19T03:25:00.000Z",
      "speed": 35,
      "isStop": false
    },
    {
      "lat": 28.67618,
      "lng": 77.38354,
      "timestamp": "2024-12-19T03:27:00.000Z",
      "speed": 40,
      "isStop": false
    },
    {
      "lat": 28.677925000000002,
      "lng": 77.365975,
      "timestamp": "2024-12-19T03:29:00.000Z",
      "speed": 28,
      "isStop": false
    },
    {
      "lat": 28.67967,
      "lng": 77.34841,
      "timestamp": "2024-12-19T03:31:00.000Z",
      "speed": 44,
      "isStop": false
    },
    {
      "lat": 28.681415,
      "lng": 77.330845,
      "timestamp": "2024-12-19T03:33:00.000Z",
      "speed": 21,
      "isStop": false
    },
    {
      "lat": 28.68316,
      "lng": 77.31328,
      "timestamp": "2024-12-19T03:35:00.000Z",
      "speed": 54,
      "isStop": false
    },
    {
      "lat": 28.684905,
      "lng": 77.295715,
      "timestamp": "2024-12-19T03:37:00.000Z",
      "speed": 46,
      "isStop": false
    },
    {
      "lat": 28.68665,
      "lng": 77.27815000000001,
      "timestamp": "2024-12-19T03:39:00.000Z",
      "speed": 56,
      "isStop": false
    },
    {
      "lat": 28.688395,
      "lng": 77.260585,
      "timestamp": "2024-12-19T03:41:00.000Z",
      "speed": 43,
      "isStop": false
    },
    {
      "lat": 28.69014,
      "lng": 77.24302,
      "timestamp": "2024-12-19T03:43:00.000Z",
      "speed": 39,
      "isStop": false
    },
    {
      "lat": 28.691885,
      "lng": 77.22545500000001,
      "timestamp": "2024-12-19T03:45:00.000Z",
      "speed": 32,
      "isStop": false
    },
    {
      "lat": 28.69363,
      "lng": 77.20789,
      "timestamp": "2024-12-19T03:47:00.000Z",
      "speed": 51,
      "isStop": false
    },
    {
      "lat": 28.695375,
      "lng": 77.190325,
      "timestamp": "2024-12-19T03:49:00.000Z",
      "speed": 55,
      "isStop": false
    },
    {
      "lat": 28.69712,
      "lng": 77.17276000000001,
      "timestamp": "2024-12-19T03:51:00.000Z",
      "speed": 49,
      "isStop": false
    },
    {
      "lat": 28.698865,
      "lng": 77.155195,
      "timestamp": "2024-12-19T03:53:00.000Z",
      "speed": 41,
      "isStop": false
    },
    {
      "lat": 28.70061,
      "lng": 77.13763,
      "timestamp": "2024-12-19T03:55:00.000Z",
      "speed": 27,
      "isStop": false
    },
    {
      "lat": 28.702355,
      "lng": 77.12006500000001,
      "timestamp": "2024-12-19T03:57:00.000Z",
      "speed": 52,
      "isStop": false
    },
    {
      "lat": 28.7041,
      "lng": 77.1025,
      "timestamp": "2024-12-19T03:59:00.000Z",
      "speed": 0,
      "isStop": false
    }
  ],
  "summary": {
    "totalDistance": 70.6,
    "drivingDuration": 144,
    "idleDuration": 40,
    "maxSpeed": 105,
    "avgSpeed": 45,
    "stops": 4
  }
}