{
  "points": [
    {
      "lat": 28.5244,
      "lng": 77.1855,
      "timestamp": "2025-12-07T00:30:00.000Z",
      "speed": 0,
      "isStop": false
    },
    {
      "lat": 28.521155,
      "lng": 77.177555,
      "timestamp": "2025-12-07T00:35:00.000Z",
      "speed": 46,
      "isStop": false
    },
    {
      "lat": 28.51791,
      "lng": 77.16961,
      "timestamp": "2025-12-07T00:37:00.000Z",
      "speed": 37,
      "isStop": false
    },
    {
      "lat": 28.514665,
      "lng": 77.161665,
      "timestamp": "2025-12-07T00:39:00.000Z",
      "speed": 39,
      "isStop": false
    },
    {
      "lat": 28.51142,
      "lng": 77.15372,
      "timestamp": "2025-12-07T00:41:00.000Z",
      "speed": 43,
      "isStop": false
    },
    {
      "lat": 28.508175,
      "lng": 77.145775,
      "timestamp": "2025-12-07T00:43:00.000Z",
      "speed": 44,
      "isStop": false
    },
    {
      "lat": 28.504929999999998,
      "lng": 77.13783000000001,
      "timestamp": "2025-12-07T00:45:00.000Z",
      "speed": 44,
      "isStop": false
    },
    {
      "lat": 28.501685,
      "lng": 77.129885,
      "timestamp": "2025-12-07T00:47:00.000Z",
      "speed": 53,
      "isStop": false
    },
    {
      "lat": 28.49844,
      "lng": 77.12194000000001,
      "timestamp": "2025-12-07T00:49:00.000Z",
      "speed": 58,
      "isStop": false
    },
    {
      "lat": 28.495195,
      "lng": 77.113995,
      "timestamp": "2025-12-07T00:51:00.000Z",
      "speed": 52,
      "isStop": false
    },
    {
      "lat": 28.49195,
      "lng": 77.10605000000001,
      "timestamp": "2025-12-07T00:53:00.000Z",
      "speed": 32,
      "isStop": false
    },
    {
      "lat": 28.488705,
      "lng": 77.098105,
      "timestamp": "2025-12-07T00:55:00.000Z",
      "speed": 54,
      "isStop": false
    },
    {
      "lat": 28.48546,
      "lng": 77.09016,
      "timestamp": "2025-12-07T00:57:00.000Z",
      "speed": 36,
      "isStop": false
    },
    {
      "lat": 28.482215,
      "lng": 77.082215,
      "timestamp": "2025-12-07T00:59:00.000Z",
      "speed": 20,
      "isStop": false
    },
    {
      "lat": 28.47897,
      "lng": 77.07427,
      "timestamp": "2025-12-07T01:01:00.000Z",
      "speed": 82,
      "isStop": false
    },
    {
      "lat": 28.475724999999997,
      "lng": 77.066325,
      "timestamp": "2025-12-07T01:03:00.000Z",
      "speed": 35,
      "isStop": false
    },
    {
      "lat": 28.472479999999997,
      "lng": 77.05838,
      "timestamp": "2025-12-07T01:05:00.000Z",
      "speed": 50,
      "isStop": false
    },
    {
      "lat": 28.469234999999998,
      "lng": 77.05043500000001,
      "timestamp": "2025-12-07T01:07:00.000Z",
      "speed": 53,
      "isStop": false
    },
    {
      "lat": 28.465989999999998,
      "lng": 77.04249,
      "timestamp": "2025-12-07T01:09:00.000Z",
      "speed": 49,
      "isStop": false
    },
    {
      "lat": 28.462744999999998,
      "lng": 77.03454500000001,
      "timestamp": "2025-12-07T01:11:00.000Z",
      "speed": 61,
      "isStop": false
    },
    {
      "lat": 28.4595,
      "lng": 77.0266,
      "timestamp": "2025-12-07T01:13:00.000Z",
      "speed": 0,
      "isStop": false
    },
    {
      "lat": 28.4595,
      "lng": 77.0266,
      "timestamp": "2025-12-07T01:35:00.000Z",
      "speed": 0,
      "isStop": false
    },
    {
      "lat": 28.47308888888889,
      "lng": 77.03081666666667,
      "timestamp": "2025-12-07T01:40:00.000Z",
      "speed": 47,
      "isStop": false
    },
    {
      "lat": 28.486677777777775,
      "lng": 77.03503333333333,
      "timestamp": "2025-12-07T01:42:00.000Z",
      "speed": 38,
      "isStop": false
    },
    {
      "lat": 28.500266666666665,
      "lng": 77.03925000000001,
      "timestamp": "2025-12-07T01:44:00.000Z",
      "speed": 54,
      "isStop": false
    },
    {
      "lat": 28.513855555555555,
      "lng": 77.04346666666667,
      "timestamp": "2025-12-07T01:46:00.000Z",
      "speed": 30,
      "isStop": false
    },
    {
      "lat": 28.527444444444445,
      "lng": 77.04768333333334,
      "timestamp": "2025-12-07T01:48:00.000Z",
      "speed": 32,
      "isStop": false
    },
    {
      "lat": 28.54103333333333,
      "lng": 77.0519,
      "timestamp": "2025-12-07T01:50:00.000Z",
      "speed": 94,
      "isStop": false
    },
    {
      "lat": 28.55462222222222,
      "lng": 77.05611666666667,
      "timestamp": "2025-12-07T01:52:00.000Z",
      "speed": 55,
      "isStop": false
    },
    {
      "lat": 28.56821111111111,
      "lng": 77.06033333333333,
      "timestamp": "2025-12-07T01:54:00.000Z",
      "speed": 27,
      "isStop": false
    },
    {
      "lat": 28.5818,
      "lng": 77.06455,
      "timestamp": "2025-12-07T01:56:00.000Z",
      "speed": 48,
      "isStop": false
    },
    {
      "lat": 28.595388888888888,
      "lng": 77.06876666666668,
      "timestamp": "2025-12-07T01:58:00.000Z",
      "speed": 41,
      "isStop": false
    },
    {
      "lat": 28.608977777777778,
      "lng": 77.07298333333334,
      "timestamp": "2025-12-07T02:00:00.000Z",
      "speed": 34,
      "isStop": false
    },
    {
      "lat": 28.622566666666668,
      "lng": 77.0772,
      "timestamp": "2025-12-07T02:02:00.000Z",
      "speed": 30,
      "isStop": false
    },
    {
      "lat": 28.636155555555554,
      "lng": 77.08141666666667,
      "timestamp": "2025-12-07T02:04:00.000Z",
      "speed": 51,
      "isStop": false
    },
    {
      "lat": 28.649744444444444,
      "lng": 77.08563333333333,
      "timestamp": "2025-12-07T02:06:00.000Z",
      "speed": 35,
      "isStop": false
    },
    {
      "lat": 28.663333333333334,
      "lng": 77.08985000000001,
      "timestamp": "2025-12-07T02:08:00.000Z",
      "speed": 41,
      "isStop": false
    },
    {
      "lat": 28.676922222222224,
      "lng": 77.09406666666668,
      "timestamp": "2025-12-07T02:10:00.000Z",
      "speed": 53,
      "isStop": false
    },
    {
      "lat": 28.69051111111111,
      "lng": 77.09828333333334,
      "timestamp": "2025-12-07T02:12:00.000Z",
      "speed": 43,
      "isStop": false
    },
    {
      "lat": 28.7041,
      "lng": 77.1025,
      "timestamp": "2025-12-07T02:14:00.000Z",
      "speed": 0,
      "isStop": false
    },
    {
      "lat": 28.7041,
      "lng": 77.1025,
      "timestamp": "2025-12-07T02:42:00.000Z",
      "speed": 0,
      "isStop": false
    },
    {
      "lat": 28.69668787878788,
      "lng": 77.1002,
      "timestamp": "2025-12-07T02:47:00.000Z",
      "speed": 38,
      "isStop": false
    },
    {
      "lat": 28.689275757575757,
      "lng": 77.09790000000001,
      "timestamp": "2025-12-07T02:49:00.000Z",
      "speed": 38,
      "isStop": false
    },
    {
      "lat": 28.681863636363637,
      "lng": 77.0956,
      "timestamp": "2025-12-07T02:51:00.000Z",
      "speed": 30,
      "isStop": false
    },
    {
      "lat": 28.674451515151514,
      "lng": 77.0933,
      "timestamp": "2025-12-07T02:53:00.000Z",
      "speed": 33,
      "isStop": false
    },
    {
      "lat": 28.667039393939394,
      "lng": 77.09100000000001,
      "timestamp": "2025-12-07T02:55:00.000Z",
      "speed": 30,
      "isStop": false
    },
    {
      "lat": 28.659627272727274,
      "lng": 77.0887,
      "timestamp": "2025-12-07T02:57:00.000Z",
      "speed": 42,
      "isStop": false
    },
    {
      "lat": 28.65221515151515,
      "lng": 77.08640000000001,
      "timestamp": "2025-12-07T02:59:00.000Z",
      "speed": 45,
      "isStop": false
    },
    {
      "lat": 28.64480303030303,
      "lng": 77.0841,
      "timestamp": "2025-12-07T03:01:00.000Z",
      "speed": 20,
      "isStop": false
    },
    {
      "lat": 28.637390909090907,
      "lng": 77.0818,
      "timestamp": "2025-12-07T03:03:00.000Z",
      "speed": 59,
      "isStop": false
    },
    {
      "lat": 28.629978787878787,
      "lng": 77.07950000000001,
      "timestamp": "2025-12-07T03:05:00.000Z",
      "speed": 27,
      "isStop": false
    },
    {
      "lat": 28.622566666666668,
      "lng": 77.0772,
      "timestamp": "2025-12-07T03:07:00.000Z",
      "speed": 63,
      "isStop": false
    },
    {
      "lat": 28.615154545454544,
      "lng": 77.0749,
      "timestamp": "2025-12-07T03:09:00.000Z",
      "speed": 37,
      "isStop": false
    },
    {
      "lat": 28.607742424242424,
      "lng": 77.07260000000001,
      "timestamp": "2025-12-07T03:11:00.000Z",
      "speed": 35,
      "isStop": false
    },
    {
      "lat": 28.6003303030303,
      "lng": 77.0703,
      "timestamp": "2025-12-07T03:13:00.000Z",
      "speed": 54,
      "isStop": false
    },
    {
      "lat": 28.59291818181818,
      "lng": 77.068,
      "timestamp": "2025-12-07T03:15:00.000Z",
      "speed": 40,
      "isStop": false
    },
    {
      "lat": 28.58550606060606,
      "lng": 77.0657,
      "timestamp": "2025-12-07T03:17:00.000Z",
      "speed": 54,
      "isStop": false
    },
    {
      "lat": 28.578093939393938,
      "lng": 77.0634,
      "timestamp": "2025-12-07T03:19:00.000Z",
      "speed": 57,
      "isStop": false
    },
    {
      "lat": 28.570681818181818,
      "lng": 77.06110000000001,
      "timestamp": "2025-12-07T03:21:00.000Z",
      "speed": 44,
      "isStop": false
    },
    {
      "lat": 28.563269696969698,
      "lng": 77.0588,
      "timestamp": "2025-12-07T03:23:00.000Z",
      "speed": 50,
      "isStop": false
    },
    {
      "lat": 28.555857575757575,
      "lng": 77.0565,
      "timestamp": "2025-12-07T03:25:00.000Z",
      "speed": 54,
      "isStop": false
    },
    {
      "lat": 28.548445454545455,
      "lng": 77.05420000000001,
      "timestamp": "2025-12-07T03:27:00.000Z",
      "speed": 52,
      "isStop": false
    },
    {
      "lat": 28.54103333333333,
      "lng": 77.0519,
      "timestamp": "2025-12-07T03:29:00.000Z",
      "speed": 53,
      "isStop": false
    },
    {
      "lat": 28.53362121212121,
      "lng": 77.0496,
      "timestamp": "2025-12-07T03:31:00.000Z",
      "speed": 29,
      "isStop": false
    },
    {
      "lat": 28.52620909090909,
      "lng": 77.0473,
      "timestamp": "2025-12-07T03:33:00.000Z",
      "speed": 40,
      "isStop": false
    },
    {
      "lat": 28.518796969696968,
      "lng": 77.045,
      "timestamp": "2025-12-07T03:35:00.000Z",
      "speed": 27,
      "isStop": false
    },
    {
      "lat": 28.511384848484848,
      "lng": 77.0427,
      "timestamp": "2025-12-07T03:37:00.000Z",
      "speed": 60,
      "isStop": false
    },
    {
      "lat": 28.503972727272725,
      "lng": 77.0404,
      "timestamp": "2025-12-07T03:39:00.000Z",
      "speed": 40,
      "isStop": false
    },
    {
      "lat": 28.496560606060605,
      "lng": 77.0381,
      "timestamp": "2025-12-07T03:41:00.000Z",
      "speed": 103,
      "isStop": false
    },
    {
      "lat": 28.489148484848485,
      "lng": 77.03580000000001,
      "timestamp": "2025-12-07T03:43:00.000Z",
      "speed": 48,
      "isStop": false
    },
    {
      "lat": 28.48173636363636,
      "lng": 77.0335,
      "timestamp": "2025-12-07T03:45:00.000Z",
      "speed": 84,
      "isStop": false
    },
    {
      "lat": 28.47432424242424,
      "lng": 77.0312,
      "timestamp": "2025-12-07T03:47:00.000Z",
      "speed": 36,
      "isStop": false
    },
    {
      "lat": 28.46691212121212,
      "lng": 77.02890000000001,
      "timestamp": "2025-12-07T03:49:00.000Z",
      "speed": 84,
      "isStop": false
    },
    {
      "lat": 28.4595,
      "lng": 77.0266,
      "timestamp": "2025-12-07T03:51:00.000Z",
      "speed": 0,
      "isStop": false
    },
    {
      "lat": 28.4595,
      "lng": 77.0266,
      "timestamp": "2025-12-07T04:14:00.000Z",
      "speed": 0,
      "isStop": false
    },
    {
      "lat": 28.464041176470587,
      "lng": 77.03196470588236,
      "timestamp": "2025-12-07T04:19:00.000Z",
      "speed": 53,
      "isStop": false
    },
    {
      "lat": 28.468582352941176,
      "lng": 77.0373294117647,
      "timestamp": "2025-12-07T04:21:00.000Z",
      "speed": 50,
      "isStop": false
    },
    {
      "lat": 28.47312352941176,
      "lng": 77.04269411764706,
      "timestamp": "2025-12-07T04:23:00.000Z",
      "speed": 28,
      "isStop": false
    },
    {
      "lat": 28.47766470588235,
      "lng": 77.04805882352942,
      "timestamp": "2025-12-07T04:25:00.000Z",
      "speed": 52,
      "isStop": false
    },
    {
      "lat": 28.48220588235294,
      "lng": 77.05342352941177,
      "timestamp": "2025-12-07T04:27:00.000Z",
      "speed": 49,
      "isStop": false
    },
    {
      "lat": 28.48674705882353,
      "lng": 77.05878823529412,
      "timestamp": "2025-12-07T04:29:00.000Z",
      "speed": 55,
      "isStop": false
    },
    {
      "lat": 28.491288235294117,
      "lng": 77.06415294117647,
      "timestamp": "2025-12-07T04:31:00.000Z",
      "speed": 59,
      "isStop": false
    },
    {
      "lat": 28.495829411764706,
      "lng": 77.06951764705883,
      "timestamp": "2025-12-07T04:33:00.000Z",
      "speed": 58,
      "isStop": false
    },
    {
      "lat": 28.500370588235292,
      "lng": 77.07488235294117,
      "timestamp": "2025-12-07T04:35:00.000Z",
      "speed": 63,
      "isStop": false
    },
    {
      "lat": 28.50491176470588,
      "lng": 77.08024705882353,
      "timestamp": "2025-12-07T04:37:00.000Z",
      "speed": 52,
      "isStop": false
    },
    {
      "lat": 28.50945294117647,
      "lng": 77.08561176470589,
      "timestamp": "2025-12-07T04:39:00.000Z",
      "speed": 40,
      "isStop": false
    },
    {
      "lat": 28.51399411764706,
      "lng": 77.09097647058823,
      "timestamp": "2025-12-07T04:41:00.000Z",
      "speed": 31,
      "isStop": false
    },
    {
      "lat": 28.518535294117648,
      "lng": 77.09634117647059,
      "timestamp": "2025-12-07T04:43:00.000Z",
      "speed": 54,
      "isStop": false
    },
    {
      "lat": 28.523076470588236,
      "lng": 77.10170588235295,
      "timestamp": "2025-12-07T04:45:00.000Z",
      "speed": 31,
      "isStop": false
    },
    {
      "lat": 28.527617647058822,
      "lng": 77.1070705882353,
      "timestamp": "2025-12-07T04:47:00.000Z",
      "speed": 51,
      "isStop": false
    },
    {
      "lat": 28.53215882352941,
      "lng": 77.11243529411765,
      "timestamp": "2025-12-07T04:49:00.000Z",
      "speed": 43,
      "isStop": false
    },
    {
      "lat": 28.5367,
      "lng": 77.1178,
      "timestamp": "2025-12-07T04:51:00.000Z",
      "speed": 92,
      "isStop": false
    },
    {
      "lat": 28.54124117647059,
      "lng": 77.12316470588236,
      "timestamp": "2025-12-07T04:53:00.000Z",
      "speed": 36,
      "isStop": false
    },
    {
      "lat": 28.545782352941178,
      "lng": 77.1285294117647,
      "timestamp": "2025-12-07T04:55:00.000Z",
      "speed": 46,
      "isStop": false
    },
    {
      "lat": 28.550323529411763,
      "lng": 77.13389411764706,
      "timestamp": "2025-12-07T04:57:00.000Z",
      "speed": 37,
      "isStop": false
    },
    {
      "lat": 28.554864705882352,
      "lng": 77.13925882352942,
      "timestamp": "2025-12-07T04:59:00.000Z",
      "speed": 49,
      "isStop": false
    },
    {
      "lat": 28.55940588235294,
      "lng": 77.14462352941177,
      "timestamp": "2025-12-07T05:01:00.000Z",
      "speed": 39,
      "isStop": false
    },
    {
      "lat": 28.56394705882353,
      "lng": 77.14998823529412,
      "timestamp": "2025-12-07T05:03:00.000Z",
      "speed": 32,
      "isStop": false
    },
    {
      "lat": 28.56848823529412,
      "lng": 77.15535294117647,
      "timestamp": "2025-12-07T05:05:00.000Z",
      "speed": 44,
      "isStop": false
    },
    {
      "lat": 28.573029411764708,
      "lng": 77.16071764705883,
      "timestamp": "2025-12-07T05:07:00.000Z",
      "speed": 42,
      "isStop": false
    },
    {
      "lat": 28.577570588235293,
      "lng": 77.16608235294117,
      "timestamp": "2025-12-07T05:09:00.000Z",
      "speed": 40,
      "isStop": false
    },
    {
      "lat": 28.582111764705882,
      "lng": 77.17144705882353,
      "timestamp": "2025-12-07T05:11:00.000Z",
      "speed": 39,
      "isStop": false
    },
    {
      "lat": 28.58665294117647,
      "lng": 77.17681176470589,
      "timestamp": "2025-12-07T05:13:00.000Z",
      "speed": 48,
      "isStop": false
    },
    {
      "lat": 28.59119411764706,
      "lng": 77.18217647058823,
      "timestamp": "2025-12-07T05:15:00.000Z",
      "speed": 32,
      "isStop": false
    },
    {
      "lat": 28.59573529411765,
      "lng": 77.18754117647059,
      "timestamp": "2025-12-07T05:17:00.000Z",
      "speed": 29,
      "isStop": false
    },
    {
      "lat": 28.600276470588238,
      "lng": 77.19290588235295,
      "timestamp": "2025-12-07T05:19:00.000Z",
      "speed": 46,
      "isStop": false
    },
    {
      "lat": 28.604817647058823,
      "lng": 77.1982705882353,
      "timestamp": "2025-12-07T05:21:00.000Z",
      "speed": 41,
      "isStop": false
    },
    {
      "lat": 28.609358823529412,
      "lng": 77.20363529411765,
      "timestamp": "2025-12-07T05:23:00.000Z",
      "speed": 41,
      "isStop": false
    },
    {
      "lat": 28.6139,
      "lng": 77.209,
      "timestamp": "2025-12-07T05:25:00.000Z",
      "speed": 0,
      "isStop": false
    }
  ],
  "summary": {
    "totalDistance": 98.1,
    "drivingDuration": 202,
    "idleDuration": 58,
    "maxSpeed": 103,
    "avgSpeed": 46,
    "stops": 5
  }
}