{
  "points": [
    {
      "lat": 28.7041,
      "lng": 77.1025,
      "timestamp": "2024-12-03T02:30:00.000Z",
      "speed": 0,
      "isStop": false
    },
    {
      "lat": 28.699088888888888,
      "lng": 77.10841666666667,
      "timestamp": "2024-12-03T02:35:00.000Z",
      "speed": 26,
      "isStop": false
    },
    {
      "lat": 28.69407777777778,
      "lng": 77.11433333333333,
      "timestamp": "2024-12-03T02:37:00.000Z",
      "speed": 43,
      "isStop": false
    },
    {
      "lat": 28.68906666666667,
      "lng": 77.12025,
      "timestamp": "2024-12-03T02:39:00.000Z",
      "speed": 48,
      "isStop": false
    },
    {
      "lat": 28.684055555555556,
      "lng": 77.12616666666668,
      "timestamp": "2024-12-03T02:41:00.000Z",
      "speed": 65,
      "isStop": false
    },
    {
      "lat": 28.679044444444443,
      "lng": 77.13208333333334,
      "timestamp": "2024-12-03T02:43:00.000Z",
      "speed": 33,
      "isStop": false
    },
    {
      "lat": 28.674033333333334,
      "lng": 77.138,
      "timestamp": "2024-12-03T02:45:00.000Z",
      "speed": 37,
      "isStop": false
    },
    {
      "lat": 28.669022222222225,
      "lng": 77.14391666666667,
      "timestamp": "2024-12-03T02:47:00.000Z",
      "speed": 62,
      "isStop": false
    },
    {
      "lat": 28.66401111111111,
      "lng": 77.14983333333333,
      "timestamp": "2024-12-03T02:49:00.000Z",
      "speed": 52,
      "isStop": false
    },
    {
      "lat": 28.659,
      "lng": 77.15575000000001,
      "timestamp": "2024-12-03T02:51:00.000Z",
      "speed": 43,
      "isStop": false
    },
    {
      "lat": 28.65398888888889,
      "lng": 77.16166666666668,
      "timestamp": "2024-12-03T02:53:00.000Z",
      "speed": 59,
      "isStop": false
    },
    {
      "lat": 28.648977777777777,
      "lng": 77.16758333333334,
      "timestamp": "2024-12-03T02:55:00.000Z",
      "speed": 25,
      "isStop": false
    },
    {
      "lat": 28.643966666666667,
      "lng": 77.1735,
      "timestamp": "2024-12-03T02:57:00.000Z",
      "speed": 37,
      "isStop": false
    },
    {
      "lat": 28.638955555555555,
      "lng": 77.17941666666667,
      "timestamp": "2024-12-03T02:59:00.000Z",
      "speed": 59,
      "isStop": false
    },
    {
      "lat": 28.633944444444445,
      "lng": 77.18533333333333,
      "timestamp": "2024-12-03T03:01:00.000Z",
      "speed": 28,
      "isStop": false
    },
    {
      "lat": 28.628933333333336,
      "lng": 77.19125,
      "timestamp": "2024-12-03T03:03:00.000Z",
      "speed": 49,
      "isStop": false
    },
    {
      "lat": 28.623922222222223,
      "lng": 77.19716666666667,
      "timestamp": "2024-12-03T03:05:00.000Z",
      "speed": 31,
      "isStop": false
    },
    {
      "lat": 28.61891111111111,
      "lng": 77.20308333333334,
      "timestamp": "2024-12-03T03:07:00.000Z",
      "speed": 53,
      "isStop": false
    },
    {
      "lat": 28.6139,
      "lng": 77.209,
      "timestamp": "2024-12-03T03:09:00.000Z",
      "speed": 0,
      "isStop": false
    },
    {
      "lat": 28.6139,
      "lng": 77.209,
      "timestamp": "2024-12-03T03:39:00.000Z",
      "speed": 0,
      "isStop": false
    },
    {
      "lat": 28.610764,
      "lng": 77.21628,
      "timestamp": "2024-12-03T03:44:00.000Z",
      "speed": 33,
      "isStop": false
    },
    {
      "lat": 28.607628000000002,
      "lng": 77.22356,
      "timestamp": "2024-12-03T03:46:00.000Z",
      "speed": 47,
      "isStop": false
    },
    {
      "lat": 28.604492,
      "lng": 77.23084,
      "timestamp": "2024-12-03T03:48:00.000Z",
      "speed": 52,
      "isStop": false
    },
    {
      "lat": 28.601356,
      "lng": 77.23812000000001,
      "timestamp": "2024-12-03T03:50:00.000Z",
      "speed": 33,
      "isStop": false
    },
    {
      "lat": 28.59822,
      "lng": 77.2454,
      "timestamp": "2024-12-03T03:52:00.000Z",
      "speed": 88,
      "isStop": false
    },
    {
      "lat": 28.595084,
      "lng": 77.25268,
      "timestamp": "2024-12-03T03:54:00.000Z",
      "speed": 36,
      "isStop": false
    },
    {
      "lat": 28.591948000000002,
      "lng": 77.25996,
      "timestamp": "2024-12-03T03:56:00.000Z",
      "speed": 48,
      "isStop": false
    },
    {
      "lat": 28.588812,
      "lng": 77.26724,
      "timestamp": "2024-12-03T03:58:00.000Z",
      "speed": 50,
      "isStop": false
    },
    {
      "lat": 28.585676,
      "lng": 77.27452000000001,
      "timestamp": "2024-12-03T04:00:00.000Z",
      "speed": 51,
      "isStop": false
    },
    {
      "lat": 28.58254,
      "lng": 77.2818,
      "timestamp": "2024-12-03T04:02:00.000Z",
      "speed": 52,
      "isStop": false
    },
    {
      "lat": 28.579404,
      "lng": 77.28908,
      "timestamp": "2024-12-03T04:04:00.000Z",
      "speed": 29,
      "isStop": false
    },
    {
      "lat": 28.576268,
      "lng": 77.29636,
      "timestamp": "2024-12-03T04:06:00.000Z",
      "speed": 21,
      "isStop": false
    },
    {
      "lat": 28.573132,
      "lng": 77.30364,
      "timestamp": "2024-12-03T04:08:00.000Z",
      "speed": 44,
      "isStop": false
    },
    {
      "lat": 28.569996,
      "lng": 77.31092000000001,
      "timestamp": "2024-12-03T04:10:00.000Z",
      "speed": 48,
      "isStop": false
    },
    {
      "lat": 28.56686,
      "lng": 77.3182,
      "timestamp": "2024-12-03T04:12:00.000Z",
      "speed": 65,
      "isStop": false
    },
    {
      "lat": 28.563724,
      "lng": 77.32548,
      "timestamp": "2024-12-03T04:14:00.000Z",
      "speed": 32,
      "isStop": false
    },
    {
      "lat": 28.560588,
      "lng": 77.33276000000001,
      "timestamp": "2024-12-03T04:16:00.000Z",
      "speed": 62,
      "isStop": false
    },
    {
      "lat": 28.557451999999998,
      "lng": 77.34004,
      "timestamp": "2024-12-03T04:18:00.000Z",
      "speed": 46,
      "isStop": false
    },
    {
      "lat": 28.554316,
      "lng": 77.34732000000001,
      "timestamp": "2024-12-03T04:20:00.000Z",
      "speed": 32,
      "isStop": false
    },
    {
      "lat": 28.55118,
      "lng": 77.3546,
      "timestamp": "2024-12-03T04:22:00.000Z",
      "speed": 35,
      "isStop": false
    },
    {
      "lat": 28.548044,
      "lng": 77.36188,
      "timestamp": "2024-12-03T04:24:00.000Z",
      "speed": 51,
      "isStop": false
    },
    {
      "lat": 28.544908,
      "lng": 77.36916000000001,
      "timestamp": "2024-12-03T04:26:00.000Z",
      "speed": 27,
      "isStop": false
    },
    {
      "lat": 28.541771999999998,
      "lng": 77.37644,
      "timestamp": "2024-12-03T04:28:00.000Z",
      "speed": 25,
      "isStop": false
    },
    {
      "lat": 28.538636,
      "lng": 77.38372000000001,
      "timestamp": "2024-12-03T04:30:00.000Z",
      "speed": 44,
      "isStop": false
    },
    {
      "lat": 28.5355,
      "lng": 77.391,
      "timestamp": "2024-12-03T04:32:00.000Z",
      "speed": 0,
      "isStop": false
    }
  ],
  "summary": {
    "totalDistance": 34.2,
    "drivingDuration": 82,
    "idleDuration": 25,
    "maxSpeed": 88,
    "avgSpeed": 44,
    "stops": 3
  }
}